ripikutils/__init__.py
ripikutils/logsman.py
ripikutils/monitor.py
ripikutils/response_handler.py
ripikutils/running_metrics.py
ripikutils/stream.py
ripikutils/aws/__init__.py
ripikutils/aws/s3/__init__.py
ripikutils/aws/s3/delete.py
ripikutils/aws/s3/download.py
ripikutils/aws/s3/example_usage.py
ripikutils/aws/s3/get_presigned_url.py
ripikutils/aws/s3/list.py
ripikutils/aws/s3/upload.py
ripikutils/mongo/__init__.py
ripikutils/mongo/delete.py
ripikutils/mongo/example_usage.py
ripikutils/mongo/filter.py
ripikutils/mongo/insert.py
ripikutils/mongo/update.py
ripikutils/secrets/__init__.py
ripikutils/secrets/secrets_manager.py
ripikutils/vision/__init__.py
ripikutils/vision/utils.py
ripikutils-0.10.2.dist-info/METADATA
ripikutils-0.10.2.dist-info/WHEEL
ripikutils-0.10.2.dist-info/top_level.txt
ripikutils-0.10.2.dist-info/RECORD
