Metadata-Version: 2.4
Name: ripikutils
Version: 0.10.2
Summary: A utility package for AWS S3 and MongoDB operations
Home-page: https://github.com/ripiktech/ripikutils
Author: Vaibhav Agarwal
Author-email: vaibhav@ripik.ai
License: MIT
Classifier: Development Status :: 3 - Alpha
Classifier: Intended Audience :: Developers
Classifier: License :: OSI Approved :: MIT License
Classifier: Operating System :: OS Independent
Classifier: Programming Language :: Python :: 3.10
Requires-Python: >=3.10
Requires-Dist: boto3
Requires-Dist: pymongo
Requires-Dist: certifi
Requires-Dist: numpy>=1.26.3
Requires-Dist: opencv-contrib-python>=4.10.0.82
Requires-Dist: typesentry==0.2.7
Dynamic: author
Dynamic: author-email
Dynamic: classifier
Dynamic: description
Dynamic: description-content-type
Dynamic: home-page
Dynamic: license
Dynamic: requires-dist
Dynamic: requires-python
Dynamic: summary
